safeserial/__init__.py
safeserial/_core.cpp
safeserial/_core.cpython-39-darwin.so
safeserial-0.1.3.dist-info/METADATA
safeserial-0.1.3.dist-info/WHEEL
safeserial-0.1.3.dist-info/RECORD
