Metadata-Version: 2.2
Name: safeserial
Version: 0.1.3
Summary: Python bindings for SafeSerial SDK
Author-Email: Satyam Tiwary <satyam@example.com>
License: MIT
Requires-Python: >=3.8
Requires-Dist: rich>=14.2.0
Requires-Dist: textual>=0.73.0
Requires-Dist: pytest>=7.0.0
